torchdde/__init__.py
torchdde/adjoint_dde.py
torchdde/adjoint_ode.py
torchdde/integrate.py
torchdde/misc.py
torchdde/global_interpolation/__init__.py
torchdde/global_interpolation/dense_interpolation.py
torchdde/global_interpolation/linear_interpolation.py
torchdde/local_interpolation/__init__.py
torchdde/local_interpolation/base.py
torchdde/local_interpolation/first_order_interpolation.py
torchdde/local_interpolation/fourth_order_interpolation.py
torchdde/local_interpolation/third_order_interpolation.py
torchdde/solver/__init__.py
torchdde/solver/base.py
torchdde/solver/bosh3.py
torchdde/solver/dopri5.py
torchdde/solver/euler.py
torchdde/solver/implicit_euler.py
torchdde/solver/rk2.py
torchdde/solver/rk4.py
torchdde/solver/runge_kutta.py
torchdde/step_size_controller/__init__.py
torchdde/step_size_controller/adaptive.py
torchdde/step_size_controller/base.py
torchdde/step_size_controller/constant.py
torchdde-0.1.3.dist-info/METADATA
torchdde-0.1.3.dist-info/WHEEL
torchdde-0.1.3.dist-info/licenses/LICENSE
torchdde-0.1.3.dist-info/RECORD
