Metadata-Version: 2.4
Name: torchdde
Version: 0.1.3
Summary: DDE numerical solvers in Python.
Project-URL: repository, https://github.com/thibmonsel/torchdde
Author-email: thibault monsel <thibaultmonsel@gmail.com>
License:                                  Apache License
License-File: LICENSE
Keywords: deep-learning,differential-equations,dynamical-systems,neural-differential-equations,torch
Requires-Python: >=3.9
Requires-Dist: jaxtyping>=0.2.24
Requires-Dist: torch
Requires-Dist: typing-extensions>=4.5.0
